networking_mlnx/__init__.py
networking_mlnx/_i18n.py
networking_mlnx/version.py
networking_mlnx/cmd/__init__.py
networking_mlnx/cmd/eventlet/__init__.py
networking_mlnx/cmd/eventlet/agents/__init__.py
networking_mlnx/cmd/eventlet/agents/mlnx_agent.py
networking_mlnx/db/__init__.py
networking_mlnx/db/db.py
networking_mlnx/db/migration/__init__.py
networking_mlnx/db/migration/alembic_migrations/__init__.py
networking_mlnx/db/migration/alembic_migrations/env.py
networking_mlnx/db/migration/alembic_migrations/script.py.mako
networking_mlnx/db/migration/alembic_migrations/versions/CONTRACT_HEAD
networking_mlnx/db/migration/alembic_migrations/versions/EXPAND_HEAD
networking_mlnx/db/migration/alembic_migrations/versions/start_networking_mlnx.py
networking_mlnx/db/migration/alembic_migrations/versions/newton/contract/dfd1a1f22c4180_initial.py
networking_mlnx/db/migration/alembic_migrations/versions/newton/expand/5d5e04ea01d5_sdn_journal_change_data_to_text.py
networking_mlnx/db/migration/alembic_migrations/versions/newton/expand/65b6db113427b9_initial.py
networking_mlnx/db/migration/alembic_migrations/versions/newton/expand/9f30890cfbd1_adding_sdn_journal_db.py
networking_mlnx/db/migration/alembic_migrations/versions/newton/expand/d02c04effb34_adding_sdn_maintenance_db.py
networking_mlnx/db/migration/models/__init__.py
networking_mlnx/db/migration/models/head.py
networking_mlnx/db/models/__init__.py
networking_mlnx/db/models/sdn_journal_db.py
networking_mlnx/db/models/sdn_maintenance_db.py
networking_mlnx/eswitchd/__init__.py
networking_mlnx/eswitchd/eswitch_daemon.py
networking_mlnx/eswitchd/eswitch_handler.py
networking_mlnx/eswitchd/eswitch_manager.py
networking_mlnx/eswitchd/msg_handler.py
networking_mlnx/eswitchd/cli/__init__.py
networking_mlnx/eswitchd/cli/conn_utils.py
networking_mlnx/eswitchd/cli/ebr_dbg.py
networking_mlnx/eswitchd/cli/ebrctl.py
networking_mlnx/eswitchd/cli/exceptions.py
networking_mlnx/eswitchd/common/__init__.py
networking_mlnx-21.0.0.dist-info/AUTHORS
networking_mlnx-21.0.0.dist-info/LICENSE
networking_mlnx-21.0.0.dist-info/METADATA
networking_mlnx-21.0.0.dist-info/WHEEL
networking_mlnx-21.0.0.dist-info/entry_points.txt
networking_mlnx-21.0.0.dist-info/pbr.json
networking_mlnx-21.0.0.dist-info/top_level.txt
networking_mlnx-21.0.0.dist-info/RECORD
