Metadata-Version: 2.1
Name: networking-mlnx
Version: 21.0.0
Summary: Mellanox Networking
Home-page: http://www.mellanox.com/
Author: Mellanox
Author-email: openstack@mellanox.com
Classifier: Environment :: OpenStack
Classifier: Intended Audience :: Information Technology
Classifier: Intended Audience :: System Administrators
Classifier: License :: OSI Approved :: Apache Software License
Classifier: Operating System :: POSIX :: Linux
Classifier: Programming Language :: Python
Classifier: Programming Language :: Python :: 3
Classifier: Programming Language :: Python :: 3.6
Classifier: Programming Language :: Python :: 3.7
Classifier: Programming Language :: Python :: 3.8
License-File: LICENSE
License-File: AUTHORS
Requires-Dist: Babel (>=1.3)
Requires-Dist: pbr (>4.0.0)
Requires-Dist: defusedxml (>=0.5.0)
Requires-Dist: eventlet (!=0.18.3,!=0.20.1,>=0.18.2)
Requires-Dist: netaddr (>=0.7.18)
Requires-Dist: pyroute2 (>=0.5.7)
Requires-Dist: python-neutronclient (>=6.7.0)
Requires-Dist: SQLAlchemy (>=1.2.0)
Requires-Dist: six (>=1.10.0)
Requires-Dist: oslo.config (>=5.2.0)
Requires-Dist: oslo.concurrency (>=3.26.0)
Requires-Dist: oslo.privsep (>=1.32.0)
Requires-Dist: python-openstackclient (>=3.3.0)
Requires-Dist: neutron-lib (>=3.1.0)
Requires-Dist: pyzmq
Requires-Dist: neutron (>=21.0.0)
